dnbf4py/__about__.py
dnbf4py/__init__.py
dnbf4py-0.0.1.dist-info/METADATA
dnbf4py-0.0.1.dist-info/WHEEL
dnbf4py-0.0.1.dist-info/licenses/LICENSE
dnbf4py-0.0.1.dist-info/RECORD
