Metadata-Version: 2.3
Name: dnbf4py
Version: 0.0.1
Summary: Serializer/Deserializer for dotnet's BinaryFormatter format.
Project-URL: Documentation, https://github.com/yntha/dnbf4py#readme
Project-URL: Issues, https://github.com/yntha/dnbf4py/issues
Project-URL: Source, https://github.com/yntha/dnbf4py
Author-email: yntha <126660548+yntha@users.noreply.github.com>
License-Expression: GPL-3.0-or-later
License-File: LICENSE
Classifier: Development Status :: 4 - Beta
Classifier: Programming Language :: Python
Classifier: Programming Language :: Python :: 3.11
Classifier: Programming Language :: Python :: Implementation :: CPython
Classifier: Programming Language :: Python :: Implementation :: PyPy
Requires-Python: >=3.11
